pyjsonrpc/cp.py
pyjsonrpc/http.py
pyjsonrpc/tools.py
pyjsonrpc/rpcjson.py
pyjsonrpc/rpcrequest.py
pyjsonrpc/rpcresponse.py
pyjsonrpc/rpclib.py
pyjsonrpc/__init__.py
pyjsonrpc/rpcerror.py
python_jsonrpc-0.10.0.dist-info/metadata.json
python_jsonrpc-0.10.0.dist-info/WHEEL
python_jsonrpc-0.10.0.dist-info/DESCRIPTION.rst
python_jsonrpc-0.10.0.dist-info/METADATA
python_jsonrpc-0.10.0.dist-info/top_level.txt
python_jsonrpc-0.10.0.dist-info/RECORD
