Metadata-Version: 2.0
Name: python-jsonrpc
Version: 0.10.0
Summary: Python JSON-RPC Client Server Library - Simple To Use Python JSONRPC-Library
Home-page: https://github.com/gerold-penz/python-jsonrpc
Author: Gerold Penz
Author-email: gerold@halvar.at
License: UNKNOWN
Download-URL: https://github.com/gerold-penz/python-jsonrpc/raw/master/dist/python-jsonrpc-0.10.0.tar.gz
Keywords: JSONRPC,JSON-RPC,JSON,RPC,Client,Server,HTTP-Server,HTTP-Client,CGI,Remote Procedure Call,JavaScript Object Notation,CherryPy,Data Interchange,BaseHTTPServer
Platform: UNKNOWN
Classifier: Development Status :: 5 - Production/Stable
Classifier: Environment :: Web Environment
Classifier: Intended Audience :: Developers
Classifier: License :: OSI Approved :: GNU Library or Lesser General Public License (LGPL)
Classifier: License :: OSI Approved :: MIT License
Classifier: Operating System :: OS Independent
Classifier: Programming Language :: Python :: 2
Classifier: Topic :: Software Development :: Libraries :: Python Modules
Classifier: Topic :: System :: Networking
Classifier: Topic :: Internet :: WWW/HTTP
Classifier: Topic :: Internet :: WWW/HTTP :: HTTP Servers
Classifier: Topic :: Internet :: WWW/HTTP :: WSGI :: Application
Requires-Dist: munch
